LICENSE
MANIFEST.in
README.rst
setup.py
django_mississippi.egg-info/PKG-INFO
django_mississippi.egg-info/SOURCES.txt
django_mississippi.egg-info/dependency_links.txt
django_mississippi.egg-info/top_level.txt
mississippi/__init__.py
mississippi/apps.py
mississippi/conf.py
mississippi/models.py
mississippi/urls.py
mississippi/views.py
mississippi/migrations/0001_initial.py
mississippi/migrations/0002_resource_views.py
mississippi/migrations/0003_auto_20170522_0621.py
mississippi/migrations/0004_auto_20170522_0639.py
mississippi/migrations/0005_remove_siteresource_views.py
mississippi/migrations/__init__.py
mississippi/templates/mississippi/sitemap.xml
tests/__init__.py
tests/test_settings.py
tests/tests.py