Metadata-Version: 1.1
Name: django-mississippi
Version: 0.2.2
Summary: Promote resources to first class citizens for prefix-less URLs and easy sitemaps.
Home-page: https://github.com/sethlivingston/django-mississippi
Author: Seth Livingston
Author-email: webdevbyseth@gmail.com
License: ISC License
Platform: UNKNOWN
Classifier: Environment :: Web Environment
Classifier: Framework :: Django
Classifier: Framework :: Django :: 1.11
Classifier: Intended Audience :: Developers
Classifier: Programming Language :: Python
Classifier: Programming Language :: Python :: 3
Classifier: Programming Language :: Python :: 3.5
Classifier: Topic :: Internet :: WWW/HTTP
Classifier: Topic :: Internet :: WWW/HTTP :: Dynamic Content
